odoo/addons/hr_employee_service/README.rst
odoo/addons/hr_employee_service/__init__.py
odoo/addons/hr_employee_service/__manifest__.py
odoo/addons/hr_employee_service/i18n/ca.po
odoo/addons/hr_employee_service/i18n/de.po
odoo/addons/hr_employee_service/i18n/es.po
odoo/addons/hr_employee_service/i18n/fr.po
odoo/addons/hr_employee_service/i18n/hr_employee_service.pot
odoo/addons/hr_employee_service/i18n/it.po
odoo/addons/hr_employee_service/i18n/pt_BR.po
odoo/addons/hr_employee_service/i18n/tr.po
odoo/addons/hr_employee_service/models/__init__.py
odoo/addons/hr_employee_service/models/hr_employee.py
odoo/addons/hr_employee_service/readme/CONTRIBUTORS.md
odoo/addons/hr_employee_service/readme/DESCRIPTION.md
odoo/addons/hr_employee_service/static/description/icon.png
odoo/addons/hr_employee_service/static/description/index.html
odoo/addons/hr_employee_service/tests/__init__.py
odoo/addons/hr_employee_service/tests/test_hr_employee_service.py
odoo/addons/hr_employee_service/views/hr_employee.xml
odoo_addon_hr_employee_service-18.0.1.0.0.4.dist-info/METADATA
odoo_addon_hr_employee_service-18.0.1.0.0.4.dist-info/WHEEL
odoo_addon_hr_employee_service-18.0.1.0.0.4.dist-info/top_level.txt
odoo_addon_hr_employee_service-18.0.1.0.0.4.dist-info/RECORD
